lab1/lab1_7segment.sv
//Anirudh Gupta
//anirgupta@g.hmc.edu
//9/6/2026
//This module controls a 7 segment display based off switch input.
//The display shows hexidecimal representations of the 15 possible switch combinations

module segment(
	input   logic [3:0] s,
	output  logic [6:0] seg
);
	
	//Turn on segments to create 0-F based on switch inputs
	always_comb begin
		case (s)
			4'b0000: seg = 7'b1000000;
			4'b0001: seg = 7'b1111001;
			4'b0010: seg = 7'b0100100;
			4'b0011: seg = 7'b0110000;
			4'b0100: seg = 7'b0011001;
			4'b0101: seg = 7'b0010010;
			4'b0110: seg = 7'b0000010;
			4'b0111: seg = 7'b1111000;
			4'b1000: seg = 7'b0000000;
			4'b1001: seg = 7'b0010000;
			4'b1010: seg = 7'b0001000;
			4'b1011: seg = 7'b0000011;
			4'b1100: seg = 7'b1000110;
			4'b1101: seg = 7'b0100001;
			4'b1110: seg = 7'b0000110;
			4'b1111: seg = 7'b0001110;
		endcase
	end

endmodule

lab1/source/impl_1/tesbenchSEGMENT.sv
// Anirudh Gupta
// anirgupta@g.hmc.edu
// 9/7/2026
// Test bench for all 16 combinations of the 7-segment display

`timescale 1ns/1ns
`default_nettype none
`define N_TV 16

module segment_tb();

    // Set up test signals
    logic clk, reset;
    logic [3:0] s;
    logic [6:0] seg;
    logic [6:0] seg_expected;
    logic [31:0] vectornum, errors;
    logic [10:0] testvectors [10000:0]; // Vectors of format s[3:0]_seg[6:0]

    // Instantiate the device under test
    segment dut(.s(s), .seg(seg));

    // Generate clock signal with a period of 10 timesteps
    always begin
        clk = 1; #5;
        clk = 0; #5;
    end

    // At the start of the simulation:
    //  - Load the testvectors
    //  - Pulse the reset line (if applicable)
    initial begin
        $readmemb("segment_testvectors.tv", testvectors, 0, `N_TV - 1);
        vectornum = 0;
        errors = 0;

        reset = 1;
        #27;
        reset = 0;
    end

    // Apply test vector on the rising edge of clk
    always @(posedge clk) begin
        #1;
        {s[3:0], seg_expected[6:0]} = testvectors[vectornum];
    end

    // Create dumpfile for signals
    initial begin
        $dumpfile("segment_tb.vcd");
        $dumpvars(0, segment_tb);
    end

    // Check results on the falling edge of clk
    always @(negedge clk) begin
        if (~reset) begin // Skip during reset

            if (seg != seg_expected) begin
                $display("Error: inputs: s=%b", s);
                $display(" outputs: seg=%b (%b expected)", seg, seg_expected);
                errors = errors + 1;
            end

            vectornum = vectornum + 1;

            if (testvectors[vectornum] === 11'bx) begin
                $display("%d tests completed with %d errors.", vectornum, errors);
                $finish;
            end

        end
    end

endmodule

lab1/segmentsim/segment_tb.vcd
$date
	Mon Sep  7 13:19:03 2026
$end
$version
	Questa Lattice OEM Edition 2025.2
$end
$timescale
	1ns
$end

$scope module segment_tb $end
$var reg 1 ! clk $end
$var reg 1 " reset $end
$var reg 4 # s [3:0] $end
$var reg 7 $ seg [6:0] $end
$var reg 7 % seg_expected [6:0] $end
$var reg 32 & vectornum [31:0] $end
$var reg 32 ' errors [31:0] $end

$scope module dut $end
$var wire 1 ( s [3] $end
$var wire 1 ) s [2] $end
$var wire 1 * s [1] $end
$var wire 1 + s [0] $end
$var reg 7 , seg [6:0] $end
$upscope $end
$upscope $end
$enddefinitions $end
#0
$dumpvars
1!
1"
bx #
bx $
bx %
b0 &
b0 '
bx ,
x+
x*
x)
x(
$end
#1
b111111 %
b0 #
0+
0*
0)
0(
b111111 ,
b111111 $
#5
0!
#10
1!
#15
0!
#20
1!
#25
0!
#27
0"
#30
1!
#35
0!
b1 &
#40
1!
#41
b110 %
b1 #
1+
b110 ,
b110 $
#45
0!
b10 &
#50
1!
#51
b1011011 %
b10 #
0+
1*
b1011011 ,
b1011011 $
#55
0!
b11 &
#60
1!
#61
b1001111 %
b11 #
1+
b1001111 ,
b1001111 $
#65
0!
b100 &
#70
1!
#71
b1100110 %
b100 #
0+
0*
1)
b1100110 ,
b1100110 $
#75
0!
b101 &
#80
1!
#81
b1101101 %
b101 #
1+
b1101101 ,
b1101101 $
#85
0!
b110 &
#90
1!
#91
b1111101 %
b110 #
0+
1*
b1111101 ,
b1111101 $
#95
0!
b111 &
#100
1!
#101
b111 %
b111 #
1+
b111 ,
b111 $
#105
0!
b1000 &
#110
1!
#111
b1111111 %
b1000 #
0+
0*
0)
1(
b1111111 ,
b1111111 $
#115
0!
b1001 &
#120
1!
#121
b1100111 %
b1001 #
1+
b1100111 ,
b1100111 $
#125
0!
b1010 &
#130
1!
#131
b1110111 %
b1010 #
0+
1*
b1110111 ,
b1110111 $
#135
0!
b1011 &
#140
1!
#141
b1111100 %
b1011 #
1+
b1111100 ,
b1111100 $
#145
0!
b1100 &
#150
1!
#151
b111001 %
b1100 #
0+
0*
1)
b111001 ,
b111001 $
#155
0!
b1101 &
#160
1!
#161
b1011110 %
b1101 #
1+
b1011110 ,
b1011110 $
#165
0!
b1110 &
#170
1!
#171
b1111001 %
b1110 #
0+
1*
b1111001 ,
b1111001 $
#175
0!
b1111 &
#180
1!
#181
b1110001 %
b1111 #
1+
b1110001 ,
b1110001 $
#185
0!
b10000 &
